odoo10_addon_knowledge-10.0.1.0.0.99.dev24-py3.8-nspkg.pth
odoo/addons/knowledge/README.rst
odoo/addons/knowledge/__init__.py
odoo/addons/knowledge/__manifest__.py
odoo/addons/knowledge/data/ir_module_category.xml
odoo/addons/knowledge/demo/knowledge.xml
odoo/addons/knowledge/i18n/am.po
odoo/addons/knowledge/i18n/ar.po
odoo/addons/knowledge/i18n/bg.po
odoo/addons/knowledge/i18n/bs.po
odoo/addons/knowledge/i18n/ca.po
odoo/addons/knowledge/i18n/cs.po
odoo/addons/knowledge/i18n/da.po
odoo/addons/knowledge/i18n/de.po
odoo/addons/knowledge/i18n/el.po
odoo/addons/knowledge/i18n/el_GR.po
odoo/addons/knowledge/i18n/en_AU.po
odoo/addons/knowledge/i18n/en_GB.po
odoo/addons/knowledge/i18n/es.po
odoo/addons/knowledge/i18n/es_AR.po
odoo/addons/knowledge/i18n/es_CL.po
odoo/addons/knowledge/i18n/es_CO.po
odoo/addons/knowledge/i18n/es_CR.po
odoo/addons/knowledge/i18n/es_DO.po
odoo/addons/knowledge/i18n/es_EC.po
odoo/addons/knowledge/i18n/es_ES.po
odoo/addons/knowledge/i18n/es_MX.po
odoo/addons/knowledge/i18n/es_PY.po
odoo/addons/knowledge/i18n/es_VE.po
odoo/addons/knowledge/i18n/et.po
odoo/addons/knowledge/i18n/eu.po
odoo/addons/knowledge/i18n/fa.po
odoo/addons/knowledge/i18n/fi.po
odoo/addons/knowledge/i18n/fr.po
odoo/addons/knowledge/i18n/fr_CA.po
odoo/addons/knowledge/i18n/gl.po
odoo/addons/knowledge/i18n/gu.po
odoo/addons/knowledge/i18n/he.po
odoo/addons/knowledge/i18n/hi.po
odoo/addons/knowledge/i18n/hr.po
odoo/addons/knowledge/i18n/hu.po
odoo/addons/knowledge/i18n/hy.po
odoo/addons/knowledge/i18n/id.po
odoo/addons/knowledge/i18n/is.po
odoo/addons/knowledge/i18n/it.po
odoo/addons/knowledge/i18n/ja.po
odoo/addons/knowledge/i18n/ka.po
odoo/addons/knowledge/i18n/kab.po
odoo/addons/knowledge/i18n/kk.po
odoo/addons/knowledge/i18n/knowledge.pot
odoo/addons/knowledge/i18n/ko.po
odoo/addons/knowledge/i18n/ln.po
odoo/addons/knowledge/i18n/lo.po
odoo/addons/knowledge/i18n/lt.po
odoo/addons/knowledge/i18n/lv.po
odoo/addons/knowledge/i18n/mk.po
odoo/addons/knowledge/i18n/mn.po
odoo10_addon_knowledge-10.0.1.0.0.99.dev24.dist-info/METADATA
odoo10_addon_knowledge-10.0.1.0.0.99.dev24.dist-info/WHEEL
odoo10_addon_knowledge-10.0.1.0.0.99.dev24.dist-info/namespace_packages.txt
odoo10_addon_knowledge-10.0.1.0.0.99.dev24.dist-info/top_level.txt
odoo10_addon_knowledge-10.0.1.0.0.99.dev24.dist-info/RECORD
